romanspec/__init__.py
romanspec/ann.py
romanspec/monte.py
romanspec/utils.py
romanspec/data/ann_29pars_3500-4200.pkl
romanspec/data/ann_29pars_4000-5000.pkl
romanspec/data/ann_29pars_4900-6000.pkl
romanspec/data/apogeedr17_rgb_feh_ann.npz
romanspec/data/apogeedr17_rgb_logg_ann.npz
romanspec-1.0.0.dist-info/LICENSE
romanspec-1.0.0.dist-info/METADATA
romanspec-1.0.0.dist-info/WHEEL
romanspec-1.0.0.dist-info/entry_points.txt
romanspec-1.0.0.dist-info/top_level.txt
romanspec-1.0.0.dist-info/RECORD
